{
  "group_stage": [
    {
      "match": 1,
      "home": "Mexico",
      "away": "South Africa",
      "home_goals": 2,
      "away_goals": 0,
      "play_order": 1
    },
    {
      "match": 2,
      "home": "Korea Republic",
      "away": "Czech Republic",
      "home_goals": 2,
      "away_goals": 1,
      "play_order": 2
    },
    {
      "match": 3,
      "home": "Canada",
      "away": "Bosnia and Herzegovina",
      "home_goals": 1,
      "away_goals": 1,
      "play_order": 3
    },
    {
      "match": 4,
      "home": "United States",
      "away": "Paraguay",
      "home_goals": 4,
      "away_goals": 1,
      "play_order": 4
    },
    {
      "match": 5,
      "home": "Haiti",
      "away": "Scotland",
      "home_goals": 0,
      "away_goals": 1,
      "play_order": 7
    },
    {
      "match": 6,
      "home": "Australia",
      "away": "Turkey",
      "home_goals": 2,
      "away_goals": 0,
      "play_order": 8
    },
    {
      "match": 7,
      "home": "Brazil",
      "away": "Morocco",
      "home_goals": 1,
      "away_goals": 1,
      "play_order": 6
    },
    {
      "match": 8,
      "home": "Qatar",
      "away": "Switzerland",
      "home_goals": 1,
      "away_goals": 1,
      "play_order": 5
    },
    {
      "match": 9,
      "home": "Ivory Coast",
      "away": "Ecuador",
      "home_goals": 1,
      "away_goals": 0,
      "play_order": 11
    },
    {
      "match": 10,
      "home": "Germany",
      "away": "Curaçao",
      "home_goals": 7,
      "away_goals": 1,
      "play_order": 9
    },
    {
      "match": 11,
      "home": "Netherlands",
      "away": "Japan",
      "home_goals": 2,
      "away_goals": 2,
      "play_order": 10
    },
    {
      "match": 12,
      "home": "Sweden",
      "away": "Tunisia",
      "home_goals": 5,
      "away_goals": 1,
      "play_order": 12
    },
    {
      "match": 13,
      "home": "Saudi Arabia",
      "away": "Uruguay",
      "home_goals": 1,
      "away_goals": 1,
      "play_order": 15
    },
    {
      "match": 14,
      "home": "Spain",
      "away": "Cape Verde",
      "home_goals": 0,
      "away_goals": 0,
      "play_order": 13
    },
    {
      "match": 15,
      "home": "Iran",
      "away": "New Zealand",
      "home_goals": 2,
      "away_goals": 2,
      "play_order": 16
    },
    {
      "match": 16,
      "home": "Belgium",
      "away": "Egypt",
      "home_goals": 1,
      "away_goals": 1,
      "play_order": 14
    },
    {
      "match": 17,
      "home": "France",
      "away": "Senegal",
      "home_goals": 3,
      "away_goals": 1,
      "play_order": 17
    },
    {
      "match": 18,
      "home": "Iraq",
      "away": "Norway",
      "home_goals": 1,
      "away_goals": 4,
      "play_order": 18
    },
    {
      "match": 19,
      "home": "Argentina",
      "away": "Algeria",
      "home_goals": 3,
      "away_goals": 0,
      "play_order": 19
    },
    {
      "match": 20,
      "home": "Austria",
      "away": "Jordan",
      "home_goals": 3,
      "away_goals": 1,
      "play_order": 20
    },
    {
      "match": 21,
      "home": "Ghana",
      "away": "Panama",
      "home_goals": 1,
      "away_goals": 0,
      "play_order": 23
    },
    {
      "match": 22,
      "home": "England",
      "away": "Croatia",
      "home_goals": 4,
      "away_goals": 2,
      "play_order": 22
    },
    {
      "match": 23,
      "home": "Portugal",
      "away": "DR Congo",
      "home_goals": 1,
      "away_goals": 1,
      "play_order": 21
    },
    {
      "match": 24,
      "home": "Uzbekistan",
      "away": "Colombia",
      "home_goals": 1,
      "away_goals": 3,
      "play_order": 24
    },
    {
      "match": 25,
      "home": "Czech Republic",
      "away": "South Africa",
      "home_goals": 1,
      "away_goals": 1,
      "play_order": 25
    },
    {
      "match": 26,
      "home": "Switzerland",
      "away": "Bosnia and Herzegovina",
      "home_goals": 4,
      "away_goals": 1,
      "play_order": 26
    },
    {
      "match": 27,
      "home": "Canada",
      "away": "Qatar",
      "home_goals": 6,
      "away_goals": 0,
      "play_order": 27
    },
    {
      "match": 28,
      "home": "Mexico",
      "away": "Korea Republic",
      "home_goals": 1,
      "away_goals": 0,
      "play_order": 28
    },
    {
      "match": 29,
      "home": "Brazil",
      "away": "Haiti",
      "home_goals": 3,
      "away_goals": 0,
      "play_order": 31
    },
    {
      "match": 30,
      "home": "Scotland",
      "away": "Morocco",
      "home_goals": 0,
      "away_goals": 1,
      "play_order": 30
    },
    {
      "match": 31,
      "home": "United States",
      "away": "Australia",
      "home_goals": 2,
      "away_goals": 0,
      "play_order": 32
    },
    {
      "match": 32,
      "home": "Turkey",
      "away": "Paraguay",
      "home_goals": 0,
      "away_goals": 1,
      "play_order": 29
    },
    {
      "match": 35,
      "home": "Netherlands",
      "away": "Sweden",
      "home_goals": 5,
      "away_goals": 1,
      "play_order": 33
    }
  ],
  "knockout": [],
  "world_champion": null,
  "runner_up": null,
  "third_place": null
}